sparse_framework/__init__.py
sparse_framework/node.py
sparse_framework/protocols.py
sparse_framework/task_executor.py
sparse_framework/dl/__init__.py
sparse_framework/dl/__main__.py
sparse_framework/dl/executor.py
sparse_framework/dl/memory_buffer.py
sparse_framework/dl/model_meta_data.py
sparse_framework/dl/model_repository.py
sparse_framework/dl/node.py
sparse_framework/dl/protocols.py
sparse_framework/dl/utils.py
sparse_framework/dl/datasets/__init__.py
sparse_framework/dl/datasets/cifar10.py
sparse_framework/dl/datasets/cifar100.py
sparse_framework/dl/datasets/imagenet100.py
sparse_framework/dl/datasets/mnist_fashion.py
sparse_framework/dl/models/__init__.py
sparse_framework/dl/models/module_queue.py
sparse_framework/dl/models/small.py
sparse_framework/dl/models/vgg.py
sparse_framework/stats/__init__.py
sparse_framework/stats/__main__.py
sparse_framework/stats/file_logger.py
sparse_framework/stats/monitor_daemon.py
sparse_framework/stats/request_statistics.py
sparse_framework-1.2.0.dist-info/METADATA
sparse_framework-1.2.0.dist-info/WHEEL
sparse_framework-1.2.0.dist-info/top_level.txt
sparse_framework-1.2.0.dist-info/RECORD
