Metadata-Version: 2.1
Name: sparse-framework
Version: 1.2.0
Summary: Stream Processing Architecture for Resource Subtle Environments
Author-email: Antero Vainio <anterongugl@gmail.com>
Project-URL: Homepage, https://github.com/AnteronGitHub/sparse
Project-URL: Bug Tracker, https://github.com/AnteronGitHub/sparse/issues
Classifier: Programming Language :: Python :: 3
Classifier: License :: OSI Approved :: MIT License
Classifier: Operating System :: OS Independent
Requires-Python: >=3.7
Requires-Dist: python-dotenv ==0.21.1
Requires-Dist: psutil ==5.8.0
Requires-Dist: torch ==1.11.0
Requires-Dist: torchvision ==0.12.0
